LICENSE
MANIFEST.in
README.md
requirements.txt
setup.cfg
setup.py
django_turbosms.egg-info/PKG-INFO
django_turbosms.egg-info/SOURCES.txt
django_turbosms.egg-info/dependency_links.txt
django_turbosms.egg-info/requires.txt
django_turbosms.egg-info/top_level.txt
turbosms/__init__.py
turbosms/admin.py
turbosms/defaults.py
turbosms/lib.py
turbosms/models.py
turbosms/routers.py
turbosms/locale/ru/LC_MESSAGES/django.mo
turbosms/locale/ru/LC_MESSAGES/django.po
turbosms/locale/uk/LC_MESSAGES/django.mo
turbosms/locale/uk/LC_MESSAGES/django.po