Metadata-Version: 2.1
Name: django-turbosms
Version: 3.5.2
Summary: Turbosms.ua django integration app
Home-page: https://github.com/pmaigutyak/mp-turbosms
Author: Paul Maigutyak
Author-email: pmaigutyak@gmail.com
License: MIT
Download-URL: https://github.com/pmaigutyak/mp-turbosms/archive/3.5.2.tar.gz
Platform: UNKNOWN
License-File: LICENSE
